{
  "lastUpdate": "2026-05-02T19:11:47.761Z",
  "source": "ai-scanner",
  "items": [
    {
      "title": "Farming Etkinliği",
      "type": "event",
      "summary": "Hafta sonu özel farming etkinliği başlıyor.",
      "date": "2026-05-02T19:11:47.761Z",
      "url": "https://albiononline.com/news",
      "aiGenerated": true
    },
    {
      "title": "Farming Etkinliği",
      "type": "event",
      "summary": "Hafta sonu özel farming etkinliği başlıyor.",
      "date": "2026-05-02T18:11:47.761Z",
      "url": "https://albiononline.com/news",
      "aiGenerated": true
    },
    {
      "title": "Market Dalgalanması",
      "type": "alert",
      "summary": "Black Market fiyatlarında anormal artış gözlemlendi.",
      "date": "2026-05-02T17:11:47.761Z",
      "url": "https://albiononline.com/news",
      "aiGenerated": true
    }
  ]
}