{
  "lastUpdate": "2026-07-20T03:48:46.827Z",
  "generatedBy": "ai-scanner",
  "aiVersion": "1.0",
  "opportunities": [
    {
      "id": "opp_1784519326826_3",
      "type": "flip",
      "item": "T6_2H_CLAYMORE",
      "itemName": "Claymore",
      "from": "Martlock",
      "to": "Bridgewatch",
      "buyPrice": 111973,
      "sellPrice": 207990,
      "profit": 96017,
      "profitPercent": "85.8",
      "timestamp": "2026-07-20T03:48:46.826Z",
      "urgency": "high",
      "aiGenerated": true,
      "aiConfidence": 97
    },
    {
      "id": "opp_1784519326826_1",
      "type": "flip",
      "item": "T7_BAG",
      "itemName": "Büyük Deri Çanta",
      "from": "Lymhurst",
      "to": "Fort Sterling",
      "buyPrice": 139080,
      "sellPrice": 220656,
      "profit": 81576,
      "profitPercent": "58.7",
      "timestamp": "2026-07-20T03:48:46.826Z",
      "urgency": "high",
      "aiGenerated": true,
      "aiConfidence": 89
    },
    {
      "id": "opp_1784519326826_5",
      "type": "transport",
      "item": "T7_BAG",
      "itemName": "Büyük Deri Çanta",
      "from": "Fort Sterling",
      "to": "Caerleon",
      "buyPrice": 118640,
      "sellPrice": 179430,
      "profit": 60790,
      "profitPercent": "51.2",
      "timestamp": "2026-07-20T03:48:46.826Z",
      "urgency": "high",
      "aiGenerated": true,
      "aiConfidence": 82
    },
    {
      "id": "opp_1784519326826_7",
      "type": "crafting",
      "item": "T6_2H_CLAYMORE",
      "itemName": "Claymore",
      "from": "Bridgewatch",
      "to": "Lymhurst",
      "buyPrice": 106507,
      "sellPrice": 138186,
      "profit": 31679,
      "profitPercent": "29.7",
      "timestamp": "2026-07-20T03:48:46.826Z",
      "urgency": "low",
      "aiGenerated": true,
      "aiConfidence": 71
    },
    {
      "id": "opp_1784519326826_2",
      "type": "transport",
      "item": "T6_CAPE",
      "itemName": "Cloak",
      "from": "Bridgewatch",
      "to": "Caerleon",
      "buyPrice": 30693,
      "sellPrice": 60453,
      "profit": 29760,
      "profitPercent": "97.0",
      "timestamp": "2026-07-20T03:48:46.826Z",
      "urgency": "high",
      "aiGenerated": true,
      "aiConfidence": 70
    },
    {
      "id": "opp_1784519326826_4",
      "type": "flip",
      "item": "T7_BAG",
      "itemName": "Büyük Deri Çanta",
      "from": "Caerleon",
      "to": "Bridgewatch",
      "buyPrice": 125818,
      "sellPrice": 154048,
      "profit": 28230,
      "profitPercent": "22.4",
      "timestamp": "2026-07-20T03:48:46.826Z",
      "urgency": "low",
      "aiGenerated": true,
      "aiConfidence": 84
    },
    {
      "id": "opp_1784519326826_0",
      "type": "flip",
      "item": "T7_FOOD_SOUP",
      "itemName": "Avalonian Soup",
      "from": "Fort Sterling",
      "to": "Martlock",
      "buyPrice": 3204,
      "sellPrice": 5894,
      "profit": 2690,
      "profitPercent": "84.0",
      "timestamp": "2026-07-20T03:48:46.826Z",
      "urgency": "high",
      "aiGenerated": true,
      "aiConfidence": 72
    },
    {
      "id": "opp_1784519326826_6",
      "type": "flip",
      "item": "T7_FOOD_SOUP",
      "itemName": "Avalonian Soup",
      "from": "Thetford",
      "to": "Fort Sterling",
      "buyPrice": 2889,
      "sellPrice": 4819,
      "profit": 1930,
      "profitPercent": "66.8",
      "timestamp": "2026-07-20T03:48:46.826Z",
      "urgency": "high",
      "aiGenerated": true,
      "aiConfidence": 98
    }
  ]
}