{
  "lastUpdate": "2026-05-03T19:10:37.493Z",
  "generatedBy": "ai-scanner",
  "aiVersion": "1.0",
  "opportunities": [
    {
      "id": "opp_1777835437493_4",
      "type": "transport",
      "item": "T7_BAG",
      "itemName": "Büyük Deri Çanta",
      "from": "Bridgewatch",
      "to": "Thetford",
      "buyPrice": 135409,
      "sellPrice": 218821,
      "profit": 83412,
      "profitPercent": "61.6",
      "timestamp": "2026-05-03T19:10:37.493Z",
      "urgency": "high",
      "aiGenerated": true,
      "aiConfidence": 70
    },
    {
      "id": "opp_1777835437493_0",
      "type": "transport",
      "item": "T6_2H_CLAYMORE",
      "itemName": "Claymore",
      "from": "Bridgewatch",
      "to": "Fort Sterling",
      "buyPrice": 88426,
      "sellPrice": 141500,
      "profit": 53074,
      "profitPercent": "60.0",
      "timestamp": "2026-05-03T19:10:37.493Z",
      "urgency": "high",
      "aiGenerated": true,
      "aiConfidence": 98
    },
    {
      "id": "opp_1777835437493_2",
      "type": "transport",
      "item": "T6_BAG",
      "itemName": "Deri Sırt Çantası",
      "from": "Bridgewatch",
      "to": "Fort Sterling",
      "buyPrice": 51256,
      "sellPrice": 94083,
      "profit": 42827,
      "profitPercent": "83.6",
      "timestamp": "2026-05-03T19:10:37.493Z",
      "urgency": "high",
      "aiGenerated": true,
      "aiConfidence": 77
    },
    {
      "id": "opp_1777835437493_5",
      "type": "crafting",
      "item": "T6_CAPE",
      "itemName": "Cloak",
      "from": "Caerleon",
      "to": "Bridgewatch",
      "buyPrice": 22769,
      "sellPrice": 34259,
      "profit": 11490,
      "profitPercent": "50.5",
      "timestamp": "2026-05-03T19:10:37.493Z",
      "urgency": "high",
      "aiGenerated": true,
      "aiConfidence": 76
    },
    {
      "id": "opp_1777835437493_1",
      "type": "transport",
      "item": "T6_MOUNT_HORSE",
      "itemName": "At",
      "from": "Lymhurst",
      "to": "Thetford",
      "buyPrice": 8581,
      "sellPrice": 16023,
      "profit": 7442,
      "profitPercent": "86.7",
      "timestamp": "2026-05-03T19:10:37.493Z",
      "urgency": "high",
      "aiGenerated": true,
      "aiConfidence": 95
    },
    {
      "id": "opp_1777835437493_3",
      "type": "transport",
      "item": "T6_MOUNT_HORSE",
      "itemName": "At",
      "from": "Thetford",
      "to": "Fort Sterling",
      "buyPrice": 7588,
      "sellPrice": 13136,
      "profit": 5548,
      "profitPercent": "73.1",
      "timestamp": "2026-05-03T19:10:37.493Z",
      "urgency": "high",
      "aiGenerated": true,
      "aiConfidence": 95
    },
    {
      "id": "opp_1777835437493_6",
      "type": "transport",
      "item": "T7_FOOD_SOUP",
      "itemName": "Avalonian Soup",
      "from": "Lymhurst",
      "to": "Fort Sterling",
      "buyPrice": 3522,
      "sellPrice": 6666,
      "profit": 3144,
      "profitPercent": "89.3",
      "timestamp": "2026-05-03T19:10:37.493Z",
      "urgency": "high",
      "aiGenerated": true,
      "aiConfidence": 95
    },
    {
      "id": "opp_1777835437493_7",
      "type": "crafting",
      "item": "T6_POTION_HEAL",
      "itemName": "Healing Potion",
      "from": "Fort Sterling",
      "to": "Thetford",
      "buyPrice": 1052,
      "sellPrice": 1747,
      "profit": 695,
      "profitPercent": "66.1",
      "timestamp": "2026-05-03T19:10:37.493Z",
      "urgency": "high",
      "aiGenerated": true,
      "aiConfidence": 78
    }
  ]
}