{
  "lastUpdate": "2026-07-08T03:30:56.479Z",
  "generatedBy": "ai-scanner",
  "aiVersion": "1.0",
  "opportunities": [
    {
      "id": "opp_1783481456479_6",
      "type": "crafting",
      "item": "T8_MOUNT_HORSE",
      "itemName": "Raptor",
      "from": "Fort Sterling",
      "to": "Martlock",
      "buyPrice": 48215,
      "sellPrice": 76208,
      "profit": 27993,
      "profitPercent": "58.1",
      "timestamp": "2026-07-08T03:30:56.479Z",
      "urgency": "high",
      "aiGenerated": true,
      "aiConfidence": 92
    },
    {
      "id": "opp_1783481456479_7",
      "type": "transport",
      "item": "T6_CAPE",
      "itemName": "Cloak",
      "from": "Thetford",
      "to": "Martlock",
      "buyPrice": 27065,
      "sellPrice": 53318,
      "profit": 26253,
      "profitPercent": "97.0",
      "timestamp": "2026-07-08T03:30:56.479Z",
      "urgency": "high",
      "aiGenerated": true,
      "aiConfidence": 89
    },
    {
      "id": "opp_1783481456479_5",
      "type": "crafting",
      "item": "T8_MOUNT_HORSE",
      "itemName": "Raptor",
      "from": "Fort Sterling",
      "to": "Thetford",
      "buyPrice": 36197,
      "sellPrice": 61606,
      "profit": 25409,
      "profitPercent": "70.2",
      "timestamp": "2026-07-08T03:30:56.479Z",
      "urgency": "high",
      "aiGenerated": true,
      "aiConfidence": 91
    },
    {
      "id": "opp_1783481456479_2",
      "type": "transport",
      "item": "T6_CAPE",
      "itemName": "Cloak",
      "from": "Thetford",
      "to": "Lymhurst",
      "buyPrice": 27825,
      "sellPrice": 48075,
      "profit": 20250,
      "profitPercent": "72.8",
      "timestamp": "2026-07-08T03:30:56.479Z",
      "urgency": "high",
      "aiGenerated": true,
      "aiConfidence": 98
    },
    {
      "id": "opp_1783481456479_1",
      "type": "transport",
      "item": "T6_BAG",
      "itemName": "Deri Sırt Çantası",
      "from": "Thetford",
      "to": "Martlock",
      "buyPrice": 40504,
      "sellPrice": 59267,
      "profit": 18763,
      "profitPercent": "46.3",
      "timestamp": "2026-07-08T03:30:56.479Z",
      "urgency": "medium",
      "aiGenerated": true,
      "aiConfidence": 91
    },
    {
      "id": "opp_1783481456479_3",
      "type": "crafting",
      "item": "T7_FOOD_SOUP",
      "itemName": "Avalonian Soup",
      "from": "Caerleon",
      "to": "Lymhurst",
      "buyPrice": 3499,
      "sellPrice": 5738,
      "profit": 2239,
      "profitPercent": "64.0",
      "timestamp": "2026-07-08T03:30:56.479Z",
      "urgency": "high",
      "aiGenerated": true,
      "aiConfidence": 73
    },
    {
      "id": "opp_1783481456479_0",
      "type": "flip",
      "item": "T6_POTION_HEAL",
      "itemName": "Healing Potion",
      "from": "Caerleon",
      "to": "Lymhurst",
      "buyPrice": 1396,
      "sellPrice": 2136,
      "profit": 740,
      "profitPercent": "53.0",
      "timestamp": "2026-07-08T03:30:56.479Z",
      "urgency": "high",
      "aiGenerated": true,
      "aiConfidence": 97
    },
    {
      "id": "opp_1783481456479_4",
      "type": "flip",
      "item": "T6_POTION_HEAL",
      "itemName": "Healing Potion",
      "from": "Lymhurst",
      "to": "Caerleon",
      "buyPrice": 1097,
      "sellPrice": 1631,
      "profit": 534,
      "profitPercent": "48.7",
      "timestamp": "2026-07-08T03:30:56.479Z",
      "urgency": "medium",
      "aiGenerated": true,
      "aiConfidence": 73
    }
  ]
}