{
  "lastUpdate": "2026-06-07T14:10:11.852Z",
  "generatedBy": "ai-scanner",
  "aiVersion": "1.0",
  "opportunities": [
    {
      "id": "opp_1780841411852_0",
      "type": "transport",
      "item": "T7_CAPE",
      "itemName": "Fort Sterling Cape",
      "from": "Martlock",
      "to": "Thetford",
      "buyPrice": 88200,
      "sellPrice": 169962,
      "profit": 81762,
      "profitPercent": "92.7",
      "timestamp": "2026-06-07T14:10:11.852Z",
      "urgency": "high",
      "aiGenerated": true,
      "aiConfidence": 80
    },
    {
      "id": "opp_1780841411852_5",
      "type": "crafting",
      "item": "T7_CAPE",
      "itemName": "Fort Sterling Cape",
      "from": "Martlock",
      "to": "Caerleon",
      "buyPrice": 82829,
      "sellPrice": 156905,
      "profit": 74076,
      "profitPercent": "89.4",
      "timestamp": "2026-06-07T14:10:11.852Z",
      "urgency": "high",
      "aiGenerated": true,
      "aiConfidence": 81
    },
    {
      "id": "opp_1780841411852_7",
      "type": "crafting",
      "item": "T7_BAG",
      "itemName": "Büyük Deri Çanta",
      "from": "Fort Sterling",
      "to": "Thetford",
      "buyPrice": 132450,
      "sellPrice": 159895,
      "profit": 27445,
      "profitPercent": "20.7",
      "timestamp": "2026-06-07T14:10:11.852Z",
      "urgency": "low",
      "aiGenerated": true,
      "aiConfidence": 80
    },
    {
      "id": "opp_1780841411852_1",
      "type": "crafting",
      "item": "T6_ARMOR_PLATE",
      "itemName": "Plate Armor",
      "from": "Bridgewatch",
      "to": "Thetford",
      "buyPrice": 77361,
      "sellPrice": 102716,
      "profit": 25355,
      "profitPercent": "32.8",
      "timestamp": "2026-06-07T14:10:11.852Z",
      "urgency": "medium",
      "aiGenerated": true,
      "aiConfidence": 99
    },
    {
      "id": "opp_1780841411852_6",
      "type": "crafting",
      "item": "T6_MOUNT_HORSE",
      "itemName": "At",
      "from": "Caerleon",
      "to": "Fort Sterling",
      "buyPrice": 8160,
      "sellPrice": 12696,
      "profit": 4536,
      "profitPercent": "55.6",
      "timestamp": "2026-06-07T14:10:11.852Z",
      "urgency": "high",
      "aiGenerated": true,
      "aiConfidence": 71
    },
    {
      "id": "opp_1780841411852_2",
      "type": "crafting",
      "item": "T6_MOUNT_HORSE",
      "itemName": "At",
      "from": "Lymhurst",
      "to": "Fort Sterling",
      "buyPrice": 10009,
      "sellPrice": 13871,
      "profit": 3862,
      "profitPercent": "38.6",
      "timestamp": "2026-06-07T14:10:11.852Z",
      "urgency": "medium",
      "aiGenerated": true,
      "aiConfidence": 98
    },
    {
      "id": "opp_1780841411852_4",
      "type": "transport",
      "item": "T6_MOUNT_HORSE",
      "itemName": "At",
      "from": "Lymhurst",
      "to": "Thetford",
      "buyPrice": 7017,
      "sellPrice": 9884,
      "profit": 2867,
      "profitPercent": "40.9",
      "timestamp": "2026-06-07T14:10:11.852Z",
      "urgency": "medium",
      "aiGenerated": true,
      "aiConfidence": 93
    },
    {
      "id": "opp_1780841411852_3",
      "type": "crafting",
      "item": "T6_MOUNT_HORSE",
      "itemName": "At",
      "from": "Fort Sterling",
      "to": "Caerleon",
      "buyPrice": 7215,
      "sellPrice": 9644,
      "profit": 2429,
      "profitPercent": "33.7",
      "timestamp": "2026-06-07T14:10:11.852Z",
      "urgency": "medium",
      "aiGenerated": true,
      "aiConfidence": 72
    }
  ]
}