{
  "lastUpdate": "2026-07-14T03:15:24.967Z",
  "generatedBy": "ai-scanner",
  "aiVersion": "1.0",
  "opportunities": [
    {
      "id": "opp_1783998924967_4",
      "type": "transport",
      "item": "T7_BAG",
      "itemName": "Büyük Deri Çanta",
      "from": "Fort Sterling",
      "to": "Martlock",
      "buyPrice": 128676,
      "sellPrice": 256824,
      "profit": 128148,
      "profitPercent": "99.6",
      "timestamp": "2026-07-14T03:15:24.967Z",
      "urgency": "high",
      "aiGenerated": true,
      "aiConfidence": 98
    },
    {
      "id": "opp_1783998924967_6",
      "type": "transport",
      "item": "T7_BAG",
      "itemName": "Büyük Deri Çanta",
      "from": "Bridgewatch",
      "to": "Thetford",
      "buyPrice": 109842,
      "sellPrice": 161075,
      "profit": 51233,
      "profitPercent": "46.6",
      "timestamp": "2026-07-14T03:15:24.967Z",
      "urgency": "medium",
      "aiGenerated": true,
      "aiConfidence": 82
    },
    {
      "id": "opp_1783998924967_2",
      "type": "crafting",
      "item": "T6_ARMOR_PLATE",
      "itemName": "Plate Armor",
      "from": "Martlock",
      "to": "Bridgewatch",
      "buyPrice": 68252,
      "sellPrice": 108566,
      "profit": 40314,
      "profitPercent": "59.1",
      "timestamp": "2026-07-14T03:15:24.967Z",
      "urgency": "high",
      "aiGenerated": true,
      "aiConfidence": 89
    },
    {
      "id": "opp_1783998924967_5",
      "type": "flip",
      "item": "T7_CAPE",
      "itemName": "Fort Sterling Cape",
      "from": "Bridgewatch",
      "to": "Caerleon",
      "buyPrice": 70761,
      "sellPrice": 105735,
      "profit": 34974,
      "profitPercent": "49.4",
      "timestamp": "2026-07-14T03:15:24.967Z",
      "urgency": "medium",
      "aiGenerated": true,
      "aiConfidence": 92
    },
    {
      "id": "opp_1783998924966_0",
      "type": "flip",
      "item": "T7_CAPE",
      "itemName": "Fort Sterling Cape",
      "from": "Fort Sterling",
      "to": "Martlock",
      "buyPrice": 88896,
      "sellPrice": 113951,
      "profit": 25055,
      "profitPercent": "28.2",
      "timestamp": "2026-07-14T03:15:24.966Z",
      "urgency": "low",
      "aiGenerated": true,
      "aiConfidence": 90
    },
    {
      "id": "opp_1783998924967_1",
      "type": "transport",
      "item": "T6_BAG",
      "itemName": "Deri Sırt Çantası",
      "from": "Fort Sterling",
      "to": "Bridgewatch",
      "buyPrice": 43603,
      "sellPrice": 67182,
      "profit": 23579,
      "profitPercent": "54.1",
      "timestamp": "2026-07-14T03:15:24.967Z",
      "urgency": "high",
      "aiGenerated": true,
      "aiConfidence": 74
    },
    {
      "id": "opp_1783998924967_3",
      "type": "transport",
      "item": "T7_FOOD_SOUP",
      "itemName": "Avalonian Soup",
      "from": "Bridgewatch",
      "to": "Fort Sterling",
      "buyPrice": 3412,
      "sellPrice": 4952,
      "profit": 1540,
      "profitPercent": "45.1",
      "timestamp": "2026-07-14T03:15:24.967Z",
      "urgency": "medium",
      "aiGenerated": true,
      "aiConfidence": 73
    },
    {
      "id": "opp_1783998924967_7",
      "type": "transport",
      "item": "T7_FOOD_SOUP",
      "itemName": "Avalonian Soup",
      "from": "Fort Sterling",
      "to": "Martlock",
      "buyPrice": 3464,
      "sellPrice": 4664,
      "profit": 1200,
      "profitPercent": "34.6",
      "timestamp": "2026-07-14T03:15:24.967Z",
      "urgency": "medium",
      "aiGenerated": true,
      "aiConfidence": 83
    }
  ]
}