{
  "lastUpdate": "2026-06-09T15:20:49.361Z",
  "generatedBy": "ai-scanner",
  "aiVersion": "1.0",
  "opportunities": [
    {
      "id": "opp_1781018449361_0",
      "type": "transport",
      "item": "T7_BAG",
      "itemName": "Büyük Deri Çanta",
      "from": "Bridgewatch",
      "to": "Thetford",
      "buyPrice": 148791,
      "sellPrice": 214616,
      "profit": 65825,
      "profitPercent": "44.2",
      "timestamp": "2026-06-09T15:20:49.361Z",
      "urgency": "medium",
      "aiGenerated": true,
      "aiConfidence": 98
    },
    {
      "id": "opp_1781018449361_7",
      "type": "transport",
      "item": "T8_MOUNT_HORSE",
      "itemName": "Raptor",
      "from": "Bridgewatch",
      "to": "Fort Sterling",
      "buyPrice": 50093,
      "sellPrice": 79672,
      "profit": 29579,
      "profitPercent": "59.0",
      "timestamp": "2026-06-09T15:20:49.361Z",
      "urgency": "high",
      "aiGenerated": true,
      "aiConfidence": 98
    },
    {
      "id": "opp_1781018449361_4",
      "type": "flip",
      "item": "T6_CAPE",
      "itemName": "Cloak",
      "from": "Martlock",
      "to": "Fort Sterling",
      "buyPrice": 24912,
      "sellPrice": 48413,
      "profit": 23501,
      "profitPercent": "94.3",
      "timestamp": "2026-06-09T15:20:49.361Z",
      "urgency": "high",
      "aiGenerated": true,
      "aiConfidence": 92
    },
    {
      "id": "opp_1781018449361_3",
      "type": "flip",
      "item": "T8_MOUNT_HORSE",
      "itemName": "Raptor",
      "from": "Bridgewatch",
      "to": "Martlock",
      "buyPrice": 40153,
      "sellPrice": 56551,
      "profit": 16398,
      "profitPercent": "40.8",
      "timestamp": "2026-06-09T15:20:49.361Z",
      "urgency": "medium",
      "aiGenerated": true,
      "aiConfidence": 94
    },
    {
      "id": "opp_1781018449361_1",
      "type": "transport",
      "item": "T6_MOUNT_HORSE",
      "itemName": "At",
      "from": "Caerleon",
      "to": "Lymhurst",
      "buyPrice": 7359,
      "sellPrice": 14126,
      "profit": 6767,
      "profitPercent": "92.0",
      "timestamp": "2026-06-09T15:20:49.361Z",
      "urgency": "high",
      "aiGenerated": true,
      "aiConfidence": 70
    },
    {
      "id": "opp_1781018449361_5",
      "type": "crafting",
      "item": "T7_FOOD_SOUP",
      "itemName": "Avalonian Soup",
      "from": "Martlock",
      "to": "Bridgewatch",
      "buyPrice": 2841,
      "sellPrice": 5484,
      "profit": 2643,
      "profitPercent": "93.0",
      "timestamp": "2026-06-09T15:20:49.361Z",
      "urgency": "high",
      "aiGenerated": true,
      "aiConfidence": 97
    },
    {
      "id": "opp_1781018449361_6",
      "type": "flip",
      "item": "T7_FOOD_SOUP",
      "itemName": "Avalonian Soup",
      "from": "Fort Sterling",
      "to": "Lymhurst",
      "buyPrice": 3362,
      "sellPrice": 5245,
      "profit": 1883,
      "profitPercent": "56.0",
      "timestamp": "2026-06-09T15:20:49.361Z",
      "urgency": "high",
      "aiGenerated": true,
      "aiConfidence": 91
    },
    {
      "id": "opp_1781018449361_2",
      "type": "transport",
      "item": "T6_POTION_HEAL",
      "itemName": "Healing Potion",
      "from": "Thetford",
      "to": "Lymhurst",
      "buyPrice": 1343,
      "sellPrice": 1712,
      "profit": 369,
      "profitPercent": "27.5",
      "timestamp": "2026-06-09T15:20:49.361Z",
      "urgency": "low",
      "aiGenerated": true,
      "aiConfidence": 92
    }
  ]
}