{
  "lastUpdate": "2026-06-11T20:30:41.245Z",
  "generatedBy": "ai-scanner",
  "aiVersion": "1.0",
  "opportunities": [
    {
      "id": "opp_1781209841244_4",
      "type": "flip",
      "item": "T6_2H_CLAYMORE",
      "itemName": "Claymore",
      "from": "Thetford",
      "to": "Lymhurst",
      "buyPrice": 110643,
      "sellPrice": 191402,
      "profit": 80759,
      "profitPercent": "73.0",
      "timestamp": "2026-06-11T20:30:41.244Z",
      "urgency": "high",
      "aiGenerated": true,
      "aiConfidence": 87
    },
    {
      "id": "opp_1781209841244_5",
      "type": "transport",
      "item": "T7_CAPE",
      "itemName": "Fort Sterling Cape",
      "from": "Lymhurst",
      "to": "Martlock",
      "buyPrice": 70285,
      "sellPrice": 122195,
      "profit": 51910,
      "profitPercent": "73.9",
      "timestamp": "2026-06-11T20:30:41.244Z",
      "urgency": "high",
      "aiGenerated": true,
      "aiConfidence": 78
    },
    {
      "id": "opp_1781209841244_7",
      "type": "flip",
      "item": "T7_CAPE",
      "itemName": "Fort Sterling Cape",
      "from": "Fort Sterling",
      "to": "Bridgewatch",
      "buyPrice": 67790,
      "sellPrice": 117310,
      "profit": 49520,
      "profitPercent": "73.0",
      "timestamp": "2026-06-11T20:30:41.244Z",
      "urgency": "high",
      "aiGenerated": true,
      "aiConfidence": 85
    },
    {
      "id": "opp_1781209841244_0",
      "type": "crafting",
      "item": "T6_BAG",
      "itemName": "Deri Sırt Çantası",
      "from": "Caerleon",
      "to": "Bridgewatch",
      "buyPrice": 47592,
      "sellPrice": 88405,
      "profit": 40813,
      "profitPercent": "85.8",
      "timestamp": "2026-06-11T20:30:41.244Z",
      "urgency": "high",
      "aiGenerated": true,
      "aiConfidence": 96
    },
    {
      "id": "opp_1781209841244_3",
      "type": "transport",
      "item": "T7_CAPE",
      "itemName": "Fort Sterling Cape",
      "from": "Martlock",
      "to": "Bridgewatch",
      "buyPrice": 75018,
      "sellPrice": 108062,
      "profit": 33044,
      "profitPercent": "44.0",
      "timestamp": "2026-06-11T20:30:41.244Z",
      "urgency": "medium",
      "aiGenerated": true,
      "aiConfidence": 87
    },
    {
      "id": "opp_1781209841244_1",
      "type": "crafting",
      "item": "T6_ARMOR_PLATE",
      "itemName": "Plate Armor",
      "from": "Bridgewatch",
      "to": "Lymhurst",
      "buyPrice": 68325,
      "sellPrice": 85152,
      "profit": 16827,
      "profitPercent": "24.6",
      "timestamp": "2026-06-11T20:30:41.244Z",
      "urgency": "low",
      "aiGenerated": true,
      "aiConfidence": 95
    },
    {
      "id": "opp_1781209841244_2",
      "type": "crafting",
      "item": "T6_MOUNT_HORSE",
      "itemName": "At",
      "from": "Lymhurst",
      "to": "Martlock",
      "buyPrice": 7360,
      "sellPrice": 13323,
      "profit": 5963,
      "profitPercent": "81.0",
      "timestamp": "2026-06-11T20:30:41.244Z",
      "urgency": "high",
      "aiGenerated": true,
      "aiConfidence": 77
    },
    {
      "id": "opp_1781209841244_6",
      "type": "transport",
      "item": "T7_FOOD_SOUP",
      "itemName": "Avalonian Soup",
      "from": "Bridgewatch",
      "to": "Martlock",
      "buyPrice": 3820,
      "sellPrice": 6319,
      "profit": 2499,
      "profitPercent": "65.4",
      "timestamp": "2026-06-11T20:30:41.244Z",
      "urgency": "high",
      "aiGenerated": true,
      "aiConfidence": 86
    }
  ]
}